setup.py
test_distributions_linh92/Binomialdistribution.py
test_distributions_linh92/Gaussiandistribution.py
test_distributions_linh92/Generaldistribution.py
test_distributions_linh92/__init__.py
test_distributions_linh92.egg-info/PKG-INFO
test_distributions_linh92.egg-info/SOURCES.txt
test_distributions_linh92.egg-info/dependency_links.txt
test_distributions_linh92.egg-info/not-zip-safe
test_distributions_linh92.egg-info/top_level.txt