Metadata-Version: 1.0
Name: test-distributions-linh92
Version: 0.1
Summary: Gaussian and Binomial distributions
Home-page: UNKNOWN
Author: Linh Truong
Author-email: mrthlinh@gmail.com
License: UNKNOWN
Platform: UNKNOWN
